atwiki/__init__.py
atwiki/_version.py
atwiki/core.py
atwiki/parser.py
atwiki/uri.py
atwiki/test/__init__.py
atwiki/test/test_core.py
atwiki/test/test_parser.py
atwiki/test/test_uri.py
atwiki/test/tools/__init__.py
atwiki/test/tools/test_dump.py
atwiki/tools/__init__.py
atwiki/tools/dump.py
atwiki_python-0.0.11.dist-info/LICENSE
atwiki_python-0.0.11.dist-info/METADATA
atwiki_python-0.0.11.dist-info/WHEEL
atwiki_python-0.0.11.dist-info/entry_points.txt
atwiki_python-0.0.11.dist-info/top_level.txt
atwiki_python-0.0.11.dist-info/RECORD
