Metadata-Version: 2.1
Name: atwiki-python
Version: 0.0.11
Summary: Atwiki Client Library
Home-page: https://github.com/kmaehashi/atwiki-python
Author: Kenichi Maehashi
Author-email: webmaster@kenichimaehashi.com
License: MIT
Classifier: Intended Audience :: Developers
Classifier: License :: OSI Approved :: MIT License
Classifier: Programming Language :: Python
Classifier: Programming Language :: Python :: 2
Classifier: Programming Language :: Python :: 2.7
Classifier: Programming Language :: Python :: 3
Classifier: Programming Language :: Python :: 3.7
Classifier: Programming Language :: Python :: 3.8
Classifier: Programming Language :: Python :: 3.9
Classifier: Programming Language :: Python :: 3.10
Classifier: Programming Language :: Python :: 3.11
Requires-Python: >=2.7,!=3.0.*,!=3.1.*,!=3.2.*,!=3.3.*,!=3.4.*,!=3.5.*,!=3.6.*
License-File: LICENSE
Requires-Dist: BeautifulSoup4
Requires-Dist: html5lib
